{
  "project_info": {
    "project_number": "383502342599",
    "project_id": "scholar-app-b9dfc",
    "storage_bucket": "scholar-app-b9dfc.appspot.com"
  },
  "client": [
    {
      "client_info": {
        "mobilesdk_app_id": "1:383502342599:android:6043414c39e9ca1e48a1e2",
        "android_client_info": {
          "package_name": "com.example.scholar_chat"
        }
      },
      "oauth_client": [
        {
          "client_id": "383502342599-j73jf1giotd2cefgd5pk9jf8igjv7gmk.apps.googleusercontent.com",
          "client_type": 3
        }
      ],
      "api_key": [
        {
          "current_key": "AIzaSyCK37Nm59q78lxKxMLbCnnTwz3gHL_2UOY"
        }
      ],
      "services": {
        "appinvite_service": {
          "other_platform_oauth_client": [
            {
              "client_id": "383502342599-j73jf1giotd2cefgd5pk9jf8igjv7gmk.apps.googleusercontent.com",
              "client_type": 3
            }
          ]
        }
      }
    }
  ],
  "configuration_version": "1"
}